etsy_apiv3/__init__.py
etsy_apiv3/exceptions/TokenExpiredError.py
etsy_apiv3/exceptions/__init__.py
etsy_apiv3/models/Auth.py
etsy_apiv3/models/File.py
etsy_apiv3/models/ListingImageModel.py
etsy_apiv3/models/ListingModel.py
etsy_apiv3/models/ListingPropertyModel.py
etsy_apiv3/models/OfferingModel.py
etsy_apiv3/models/PaymentModel.py
etsy_apiv3/models/PriceModel.py
etsy_apiv3/models/ProductModel.py
etsy_apiv3/models/ProductionPartnerModel.py
etsy_apiv3/models/PropertyValueModel.py
etsy_apiv3/models/ReceiptModel.py
etsy_apiv3/models/RefundModel.py
etsy_apiv3/models/ReturnPolicyModel.py
etsy_apiv3/models/ReviewModel.py
etsy_apiv3/models/ShipmentModel.py
etsy_apiv3/models/ShippingCarrierModel.py
etsy_apiv3/models/ShippingProfileDestinationModel.py
etsy_apiv3/models/ShippingProfileModel.py
etsy_apiv3/models/ShippingProfileUpgradeModel.py
etsy_apiv3/models/ShopModel.py
etsy_apiv3/models/ShopSection.py
etsy_apiv3/models/TaxonomyModel.py
etsy_apiv3/models/TokenModel.py
etsy_apiv3/models/TransactionModel.py
etsy_apiv3/models/TranslationModel.py
etsy_apiv3/models/UserModel.py
etsy_apiv3/models/VariationModel.py
etsy_apiv3/models/__init__.py
etsy_apiv3/resources/ListingResource.py
etsy_apiv3/resources/PaymentResource.py
etsy_apiv3/resources/ReceiptResource.py
etsy_apiv3/resources/ReviewResource.py
etsy_apiv3/resources/ShippingProfileResource.py
etsy_apiv3/resources/ShopPolicyResource.py
etsy_apiv3/resources/ShopResource.py
etsy_apiv3/resources/UserResource.py
etsy_apiv3/resources/__init__.py
etsy_apiv3/utils/APIV3.py
etsy_apiv3/utils/EtsyListRequestException.py
etsy_apiv3/utils/EtsyOauth2Session.py
etsy_apiv3/utils/RequestException.py
etsy_apiv3/utils/Response.py
etsy_apiv3/utils/__init__.py
tests/Payment.py
tests/Receipt.py
tests/__init__.py
tests/taxonomy_test.py
tests/test_credentials.py
etsy_apiv3-2.2.8.dist-info/LICENSE
etsy_apiv3-2.2.8.dist-info/METADATA
etsy_apiv3-2.2.8.dist-info/WHEEL
etsy_apiv3-2.2.8.dist-info/top_level.txt
etsy_apiv3-2.2.8.dist-info/RECORD
