Metadata-Version: 2.1
Name: etsy-apiv3
Version: 2.2.8
Summary: Etsy APIV3 SDK
Author: Esat Yılmaz
Author-email: esatyilmaz3500@gmail.com
Classifier: Programming Language :: Python :: 3.9
Classifier: License :: OSI Approved :: MIT License
Classifier: Operating System :: OS Independent
Requires-Python: >=3.8
License-File: LICENSE
Requires-Dist: Async-OAuthlib (>=0.0.9)
Requires-Dist: pycountry (>=22.1.10)
Requires-Dist: pydantic (>=1.10.2)
Requires-Dist: requests (>=2.27.1)
Requires-Dist: requests-oauthlib (>=1.3.0)
Requires-Dist: setuptools (>=58.1.0)
